ab_test_advanced_toolkit/__init__.py
ab_test_advanced_toolkit/analyzer.py
ab_test_advanced_toolkit/data_validation.py
ab_test_advanced_toolkit/metrics.py
ab_test_advanced_toolkit/stat_significance.py
ab_test_advanced_toolkit/vizualizer.py
ab_test_advanced_toolkit-0.0.26.dist-info/METADATA
ab_test_advanced_toolkit-0.0.26.dist-info/WHEEL
ab_test_advanced_toolkit-0.0.26.dist-info/licenses/LICENSE
ab_test_advanced_toolkit-0.0.26.dist-info/RECORD
