Metadata-Version: 2.3
Name: ab-test-advanced-toolkit
Version: 0.0.26
Dynamic: Requires-Dist
Summary: An experimental Python library for advanced A/B testing analysis, leveraging statistical techniques and ML for deeper insights.
Project-URL: Homepage, https://github.com/dmitry-brazhenko/ab-test-advanced-toolkit
Project-URL: Documentation, https://github.com/dmitry-brazhenko/ab-test-advanced-toolkit/blob/main/README.md
Project-URL: Repository, https://github.com/dmitry-brazhenko/ab-test-advanced-toolkit
Author-email: Dmitry Brazhenko <brazhenko.dmitry@gmail.com>, Kirill Markin <markinkirill@gmail.com>
Maintainer-email: Dmitry Brazhenko <brazhenko.dmitry@gmail.com>, Kirill Markin <markinkirill@gmail.com>
License: MIT License
License-File: LICENSE
Requires-Python: >=3.8
